vault8/__init__.py
vault8-0.0.2.dist-info/LICENSE
vault8-0.0.2.dist-info/METADATA
vault8-0.0.2.dist-info/WHEEL
vault8-0.0.2.dist-info/top_level.txt
vault8-0.0.2.dist-info/RECORD
