Metadata-Version: 2.1
Name: vault8
Version: 0.0.2
Summary: Python library for Vault8 service
Home-page: https://github.com/cimon-io/vault8-python
Author: Eugene Ignatov
Author-email: eugene@cimon.io
Maintainer: Eugene Ignatov
Maintainer-email: eugene@cimon.io
License: UNKNOWN
Keywords: vault8
Platform: UNKNOWN
Classifier: Programming Language :: Python :: 3
Classifier: License :: OSI Approved :: MIT License
Classifier: Operating System :: OS Independent
Requires-Python: >=3.6
